[{"not_user_in_password": true, "image": null, "default_language": "vi", "is_has_symbols": false, "height": null, "max_len": 20, "password_expiration": 30, "dec_place_separator": ".", "is_has_upper_char": false, "is_ad_aut": false, "num_of_symbol": 1, "modified_by": "sys", "style_class": null, "threshold_to_lock": 5, "created_by": "Application", "change_after": 30, "parent_id": null, "dec_place_currency": 3, "time_out_expand": 0, "is_has_lower_char": false, "type": null, "description": null, "min_len": 5, "minimum_age": 0, "modified_on": "2018-06-07T14:18:08.656000", "function_id": null, "active": null, "is_has_number": false, "apply_minLength": false, "icon": null, "date_format": "dd/MM/yyyy", "sorting": null, "is_first_change": true, "custom_name": null, "alert_before": 5, "num_of_upper": 2, "default_name": null, "apply_history": null, "created_on": "2018-06-07T14:18:08.656000", "apply_maxLength": false, "session_timeOut": 0, "num_of_number": 1, "time_lock": 1, "lock_on_failed": null, "url": null, "will_expire": true, "num_of_lower": 10, "_id": "5b18b6ec23203734807f2bd6", "apply_minimum_age": true, "width": null, "history": 3}]